<?xml version="1.0" encoding="UTF-8" standalone="no"?>
<service xmlns="http://www.simplity.org/schema" name="troubleTicketUpdate"
	dbAccessType="readWrite" jmsUsage="notManaged" referredServicesToInvalidate="troubleTicketFind,troubleTicketGet">
	<inputData>
		<inputFields>
			<inputField dataType="_text" name="id" />
			<inputField dataType="_text" name="correlationId" />
			<inputField dataType="_text" name="description" />
			<inputField dataType="_text" name="severity" />
			<inputField dataType="_text" name="type" />
			<inputField dataType="_text" name="creationDate" />
			<inputField dataType="_text" name="targetResolutionDate" />
			<inputField dataType="_text" name="status" />
			<inputField dataType="_text" name="subStatus" />
			<inputField dataType="_text" name="statusChangeReason" />
			<inputField dataType="_text" name="statusChangeDate" />
			<inputField dataType="_text" name="resolutionDate" />
		</inputFields>
		<inputRecords>
			<inputRecord recordName="RelatedObject" sheetName="relatedObjects" />
			<inputRecord recordName="RelatedParty" sheetName="relatedParties" />
			<inputRecord recordName="Note" sheetName="notes" />
		</inputRecords>
	</inputData>
	<actions>
		<setValue fieldName="action" fieldValue="update"></setValue>
		<save saveAction="save" recordName="TroubleTicket">
			<childRecords>
				<relatedRecord sheetName="relatedObjects" recordName="RelatedObject" />
				<relatedRecord sheetName="relatedParties" recordName="RelatedParty" />
				<relatedRecord sheetName="notes" recordName="Note" />
			</childRecords>
		</save>
		<jmsProducer actionName="write2Q">
			<requestDestination name="dynamicQueues/TTWriteQQ" messageBodyType="text">
				<outputData>
					<outputRecords>
						<outputRecord recordName="jmsTicket" />
						<outputRecord recordName="RelatedObject" sheetName="relatedObjects" />
						<outputRecord recordName="RelatedParty" sheetName="relatedParties"/>
						<outputRecord recordName="Note" sheetName="notes" />
					</outputRecords>
				</outputData>
			</requestDestination>
		</jmsProducer>
	</actions>
</service>